django_openfeature/__init__.py
django_openfeature/context.py
django_openfeature/provider.py
django_openfeature/py.typed
django_openfeature/settings.py
django_openfeature/test.py
django_openfeature/debug_toolbar/__init__.py
django_openfeature/debug_toolbar/panels.py
django_openfeature/templates/debug_toolbar/panels/feature_flags.html
django_openfeature/templatetags/__init__.py
django_openfeature/templatetags/openfeature.py
django_openfeature-0.1.4.dist-info/licenses/LICENSE
django_openfeature-0.1.4.dist-info/METADATA
django_openfeature-0.1.4.dist-info/WHEEL
django_openfeature-0.1.4.dist-info/top_level.txt
django_openfeature-0.1.4.dist-info/RECORD
