Metadata-Version: 2.4
Name: django-openfeature
Version: 0.1.4
Summary: OpenFeature integration for Django
Author-email: Federico Bond <federicobond@gmail.com>
License: MIT License
Project-URL: Homepage, https://github.com/federicobond/django-openfeature
Classifier: Development Status :: 3 - Alpha
Classifier: License :: OSI Approved :: MIT License
Classifier: Programming Language :: Python
Classifier: Programming Language :: Python :: 3
Classifier: Programming Language :: Python :: 3.10
Classifier: Programming Language :: Python :: 3.11
Classifier: Programming Language :: Python :: 3.12
Classifier: Programming Language :: Python :: 3.13
Classifier: Programming Language :: Python :: 3.14
Classifier: Framework :: Django
Requires-Python: >=3.10
License-File: LICENSE
Requires-Dist: openfeature-sdk>=0.8.3
Requires-Dist: Django>=4.2
Provides-Extra: debug-toolbar
Requires-Dist: django-debug-toolbar; extra == "debug-toolbar"
Dynamic: license-file
